ovos_skill_application_launcher/LICENSE
ovos_skill_application_launcher/MANIFEST.in
ovos_skill_application_launcher/README.md
ovos_skill_application_launcher/__init__.py
ovos_skill_application_launcher/requirements.txt
ovos_skill_application_launcher/version.py
ovos_skill_application_launcher/locale/ca-es/already_running.dialog
ovos_skill_application_launcher/locale/ca-es/close.intent
ovos_skill_application_launcher/locale/ca-es/confirm_launch.dialog
ovos_skill_application_launcher/locale/ca-es/confirm_switch.dialog
ovos_skill_application_launcher/locale/ca-es/launch.intent
ovos_skill_application_launcher/locale/ca-es/skill.json
ovos_skill_application_launcher/locale/da/already_running.dialog
ovos_skill_application_launcher/locale/da/close.intent
ovos_skill_application_launcher/locale/da/confirm_launch.dialog
ovos_skill_application_launcher/locale/da/confirm_switch.dialog
ovos_skill_application_launcher/locale/da/launch.intent
ovos_skill_application_launcher/locale/da/skill.json
ovos_skill_application_launcher/locale/de-de/already_running.dialog
ovos_skill_application_launcher/locale/de-de/close.intent
ovos_skill_application_launcher/locale/de-de/confirm_launch.dialog
ovos_skill_application_launcher/locale/de-de/confirm_switch.dialog
ovos_skill_application_launcher/locale/de-de/launch.intent
ovos_skill_application_launcher/locale/de-de/skill.json
ovos_skill_application_launcher/locale/en-us/already_running.dialog
ovos_skill_application_launcher/locale/en-us/close.intent
ovos_skill_application_launcher/locale/en-us/confirm_launch.dialog
ovos_skill_application_launcher/locale/en-us/confirm_switch.dialog
ovos_skill_application_launcher/locale/en-us/launch.intent
ovos_skill_application_launcher/locale/en-us/skill.json
ovos_skill_application_launcher/locale/eu/launch.intent
ovos_skill_application_launcher/locale/gl-es/already_running.dialog
ovos_skill_application_launcher/locale/gl-es/close.intent
ovos_skill_application_launcher/locale/gl-es/confirm_launch.dialog
ovos_skill_application_launcher/ovos_skill_application_launcher.egg-info/PKG-INFO
ovos_skill_application_launcher/ovos_skill_application_launcher.egg-info/SOURCES.txt
ovos_skill_application_launcher/ovos_skill_application_launcher.egg-info/dependency_links.txt
ovos_skill_application_launcher/ovos_skill_application_launcher.egg-info/entry_points.txt
ovos_skill_application_launcher/ovos_skill_application_launcher.egg-info/requires.txt
ovos_skill_application_launcher/ovos_skill_application_launcher.egg-info/top_level.txt
ovos_skill_application_launcher-0.5.14.dist-info/LICENSE
ovos_skill_application_launcher-0.5.14.dist-info/METADATA
ovos_skill_application_launcher-0.5.14.dist-info/WHEEL
ovos_skill_application_launcher-0.5.14.dist-info/entry_points.txt
ovos_skill_application_launcher-0.5.14.dist-info/top_level.txt
ovos_skill_application_launcher-0.5.14.dist-info/RECORD
